odoo/addons/sale_isolated_quotation/README.rst
odoo/addons/sale_isolated_quotation/__init__.py
odoo/addons/sale_isolated_quotation/__manifest__.py
odoo/addons/sale_isolated_quotation/hooks.py
odoo/addons/sale_isolated_quotation/data/ir_sequence_data.xml
odoo/addons/sale_isolated_quotation/i18n/ca.po
odoo/addons/sale_isolated_quotation/i18n/de.po
odoo/addons/sale_isolated_quotation/i18n/el_GR.po
odoo/addons/sale_isolated_quotation/i18n/es.po
odoo/addons/sale_isolated_quotation/i18n/es_ES.po
odoo/addons/sale_isolated_quotation/i18n/es_VE.po
odoo/addons/sale_isolated_quotation/i18n/fi.po
odoo/addons/sale_isolated_quotation/i18n/fr.po
odoo/addons/sale_isolated_quotation/i18n/hr.po
odoo/addons/sale_isolated_quotation/i18n/hr_HR.po
odoo/addons/sale_isolated_quotation/i18n/hu.po
odoo/addons/sale_isolated_quotation/i18n/it.po
odoo/addons/sale_isolated_quotation/i18n/nl.po
odoo/addons/sale_isolated_quotation/i18n/nl_NL.po
odoo/addons/sale_isolated_quotation/i18n/pt.po
odoo/addons/sale_isolated_quotation/i18n/pt_BR.po
odoo/addons/sale_isolated_quotation/i18n/ro.po
odoo/addons/sale_isolated_quotation/i18n/sale_isolated_quotation.pot
odoo/addons/sale_isolated_quotation/i18n/sk.po
odoo/addons/sale_isolated_quotation/i18n/sl.po
odoo/addons/sale_isolated_quotation/i18n/tr.po
odoo/addons/sale_isolated_quotation/i18n/tr_TR.po
odoo/addons/sale_isolated_quotation/i18n/vi_VN.po
odoo/addons/sale_isolated_quotation/i18n/zh_CN.po
odoo/addons/sale_isolated_quotation/migrations/12.0.1.0.0/pre-migration.py
odoo/addons/sale_isolated_quotation/models/__init__.py
odoo/addons/sale_isolated_quotation/models/sale.py
odoo/addons/sale_isolated_quotation/readme/CONTRIBUTORS.rst
odoo/addons/sale_isolated_quotation/readme/DESCRIPTION.rst
odoo/addons/sale_isolated_quotation/readme/ROADMAP.rst
odoo/addons/sale_isolated_quotation/readme/USAGE.rst
odoo/addons/sale_isolated_quotation/static/description/icon.png
odoo/addons/sale_isolated_quotation/static/description/index.html
odoo12_addon_sale_isolated_quotation-12.0.1.1.0.dist-info/METADATA
odoo12_addon_sale_isolated_quotation-12.0.1.1.0.dist-info/WHEEL
odoo12_addon_sale_isolated_quotation-12.0.1.1.0.dist-info/top_level.txt
odoo12_addon_sale_isolated_quotation-12.0.1.1.0.dist-info/RECORD
